liesym-0.8.1.dist-info/METADATA
liesym-0.8.1.dist-info/WHEEL
liesym-0.8.1.dist-info/license_files/LICENSE
liesym/groups/_so.py
liesym/groups/_u1.py
liesym/groups/__init__.py
liesym/groups/_cyclic.py
liesym/groups/_su.py
liesym/groups/_base.py
liesym/groups/_sp.py
liesym/__init__.py
liesym/algebras/_methods.py
liesym/algebras/__init__.py
liesym/algebras/_exceptionals.py
liesym/algebras/_backend.py
liesym/algebras/_base.py
liesym/algebras/_classic.py
liesym/_liesym_rust.abi3.so
liesym-0.8.1.dist-info/RECORD
