Metadata-Version: 2.1
Name: liesym
Version: 0.8.1
Classifier: Topic :: Scientific/Engineering :: Mathematics
Classifier: Topic :: Scientific/Engineering :: Physics
Classifier: Programming Language :: Rust
Classifier: Programming Language :: Python :: 3.8
Classifier: Programming Language :: Python :: 3.9
Classifier: Programming Language :: Python :: 3.10
Classifier: Programming Language :: Python :: 3.11
Requires-Dist: mpmath ==1.3.0 ; python_version >= '3.8' and python_version < '4'
Requires-Dist: numpy ==1.24.4 ; python_version >= '3.8' and python_version < '4'
Requires-Dist: symengine ==0.10.0 ; python_version >= '3.8' and python_version < '4'
Requires-Dist: sympy ==1.12 ; python_version >= '3.8' and python_version < '4'
License-File: LICENSE
Summary: Sympy Lie Algebra extensions powered by rust.
Author: Nathan Papapietro <npapapietro95@gmail.com>
Author-email: Nathan Papapietro <npapapietro95@gmail.com>
Project-URL: Documentation, https://npapapietro.github.io/liesym
Project-URL: Homepage, https://github.com/npapapietro/liesym
